README.md
setup.cfg
setup.py
eis/__init__.py
eis/billing/__init__.py
eis/billing/api_client.py
eis/billing/configuration.py
eis/billing/exceptions.py
eis/billing/model_utils.py
eis/billing/rest.py
eis/billing/api/__init__.py
eis/billing/api/correction_invoices_api.py
eis/billing/api/default_api.py
eis/billing/api/draft_invoice_api.py
eis/billing/api/estimated_invoices_api.py
eis/billing/api/initial_invoices_api.py
eis/billing/api/invoices_api.py
eis/billing/api/policy_billing_api.py
eis/billing/api/recurring_invoices_api.py
eis/billing/api/termination_invoices_api.py
eis/billing/apis/__init__.py
eis/billing/model/__init__.py
eis/billing/model/create_correction_invoices_response_class.py
eis/billing/model/create_custom_estimated_invoice_request_dto.py
eis/billing/model/create_custom_estimated_invoice_response_class.py
eis/billing/model/create_draft_invoice_request_dto.py
eis/billing/model/create_estimated_invoice_for_interval_request_dto.py
eis/billing/model/create_estimated_invoice_for_interval_response_class.py
eis/billing/model/create_estimated_invoice_request_dto.py
eis/billing/model/create_estimated_invoice_response_class.py
eis/billing/model/create_invoice_for_policy_request_dto.py
eis/billing/model/create_invoice_payment_request_dto.py
eis/billing/model/create_invoice_request_dto.py
eis/billing/model/create_invoice_response_class.py
eis/billing/model/create_invoice_status_request_dto.py
eis/billing/model/create_item_request_dto.py
eis/billing/model/create_policy_billing_request_dto.py
eis/billing/model/create_policy_billing_response_class.py
eis/billing/model/create_termination_invoice_request_dto.py
eis/billing/model/get_invoice_response_class.py
eis/billing/model/inline_response200.py
eis/billing/model/inline_response503.py
eis/billing/model/invoice_class.py
eis/billing/model/invoice_item_class.py
eis/billing/model/invoice_payment_class.py
eis/billing/model/invoice_payments_class.py
eis/billing/model/invoice_status_class.py
eis_billing.egg-info/PKG-INFO
eis_billing.egg-info/SOURCES.txt
eis_billing.egg-info/dependency_links.txt
eis_billing.egg-info/requires.txt
eis_billing.egg-info/top_level.txt
