Metadata-Version: 2.1
Name: eis-billing
Version: 1.44.0
Summary: EMIL BillingService
Home-page: UNKNOWN
Author: Contact us
Author-email: kontakt@emil.de
License: UNKNOWN
Keywords: OpenAPI,OpenAPI-Generator,EMIL BillingService
Platform: UNKNOWN
Requires-Python: >=3.6
